moderail/.gitignore
moderail/README.md
moderail/__init__.py
moderail/poetry.lock
moderail/pyproject.toml
moderail/src/__init__.py
moderail/src/config.py
moderail/src/constant.py
moderail/src/fixture/ban_words.yaml
moderail/src/helpers.py
moderail/src/registry/__init__.py
moderail/src/registry/banlist_guard.py
moderail/src/registry/banlist_streaming_guard.py
moderail/src/registry/guard.py
moderail/src/registry/llama_guard.py
moderail/src/registry/openai_moderation_guard.py
moderail/src/registry/regex_guard.py
moderail/src/registry/topic_guard.py
moderail/tests/test_banlist_guard.py
rokoai-0.1.0.dist-info/METADATA
rokoai-0.1.0.dist-info/WHEEL
rokoai-0.1.0.dist-info/RECORD
