Metadata-Version: 2.3
Name: rokoai
Version: 0.1.0
Summary: A Python package for content moderation
License: MIT
Author: Aman
Requires-Python: >=3.12,<4.0
Classifier: License :: OSI Approved :: MIT License
Classifier: Programming Language :: Python :: 3
Classifier: Programming Language :: Python :: 3.12
Classifier: Programming Language :: Python :: 3.13
